pytest_storage/__init__.py
pytest_storage/py.typed
pytest_storage-0.1.0.dist-info/METADATA
pytest_storage-0.1.0.dist-info/WHEEL
pytest_storage-0.1.0.dist-info/entry_points.txt
pytest_storage-0.1.0.dist-info/licenses/LICENSE
pytest_storage-0.1.0.dist-info/RECORD
